odoo/addons/stock_picking_delivery_link/README.rst
odoo/addons/stock_picking_delivery_link/__init__.py
odoo/addons/stock_picking_delivery_link/__manifest__.py
odoo/addons/stock_picking_delivery_link/i18n/es.po
odoo/addons/stock_picking_delivery_link/i18n/fr.po
odoo/addons/stock_picking_delivery_link/i18n/it.po
odoo/addons/stock_picking_delivery_link/i18n/stock_picking_delivery_link.pot
odoo/addons/stock_picking_delivery_link/i18n/tr.po
odoo/addons/stock_picking_delivery_link/models/__init__.py
odoo/addons/stock_picking_delivery_link/models/stock_picking.py
odoo/addons/stock_picking_delivery_link/models/stock_picking_type.py
odoo/addons/stock_picking_delivery_link/readme/CONTRIBUTORS.md
odoo/addons/stock_picking_delivery_link/readme/DESCRIPTION.md
odoo/addons/stock_picking_delivery_link/static/description/icon.png
odoo/addons/stock_picking_delivery_link/static/description/index.html
odoo/addons/stock_picking_delivery_link/tests/__init__.py
odoo/addons/stock_picking_delivery_link/tests/common.py
odoo/addons/stock_picking_delivery_link/tests/test_delivery_link.py
odoo/addons/stock_picking_delivery_link/tests/models/delivery_carrier.py
odoo/addons/stock_picking_delivery_link/views/stock_picking.xml
odoo/addons/stock_picking_delivery_link/views/stock_picking_type.xml
odoo_addon_stock_picking_delivery_link-18.0.1.0.1.1.dist-info/METADATA
odoo_addon_stock_picking_delivery_link-18.0.1.0.1.1.dist-info/WHEEL
odoo_addon_stock_picking_delivery_link-18.0.1.0.1.1.dist-info/top_level.txt
odoo_addon_stock_picking_delivery_link-18.0.1.0.1.1.dist-info/RECORD
